__init__.py
__pycache__/__init__.cpython-311.pyc
xflib/__init__.py
xflib/ps.py
xflib/ui.py
xflib/utils.py
xflib/__pycache__/__init__.cpython-311.pyc
xflib/__pycache__/ps.cpython-311.pyc
xflib/__pycache__/ui.cpython-311.pyc
xflib/__pycache__/utils.cpython-311.pyc
xflib-0.1.11.dist-info/LICENSE
xflib-0.1.11.dist-info/METADATA
xflib-0.1.11.dist-info/WHEEL
xflib-0.1.11.dist-info/top_level.txt
xflib-0.1.11.dist-info/RECORD
